Metadata-Version: 2.1
Name: SHORTCUTPRINT
Version: 0.0.1
Summary: Print and input shortcut
Home-page: https://knpjg.blogspot.com/2020/07/my-own-python-shortcutio-libiary.html
Author: KESHARI NANDANA PRATAP
Author-email: kesharipratap52@gmail.com
License: UNKNOWN
Platform: UNKNOWN
Classifier: Programming Language :: Python :: 3
Classifier: License :: OSI Approved :: MIT License
Classifier: Operating System :: OS Independent
Requires-Python: >=3.0
